{"metadata": {"date": null, "rows": 15, "cols": 15}, "clues": {"across": {"1": ["One of the most important men in modern art, per Baudelaire ", " DAUMIER"], "8": ["Dozens ", " TWELVES"], "15": ["Pointed warning? ", " ENGARDE"], "16": ["Comment after a collision ", " OHSORRY"], "17": ["They're cured! ", " SALAMIS"], "18": ["2021 No. 1 hit for Justin Bieber ", " PEACHES"], "19": ["Youth action spearheaded by Greta Thunberg in 2019 ", " CLIMATESTRIKE"], "21": ["Set of binary pronouns ", " HESHE"], "22": ["\"Wynonna ___\" (sci-fi series about the great-great-granddaughter of a legendary lawman) ", " EARP"], "25": ["Wedding count ", " RSVPS"], "30": ["Takes from the deck ", " DRAWS"], "32": ["Traffic-control org. ", " DEA"], "33": ["Subject of the 2021 documentary \"The Crime of the Century\" ", " OPIOIDS"], "35": ["Stabilizes, as an injured ankle ", " TAPESUP"], "37": ["Squeaked by ", " MADEDO"], "38": ["Lover of Endymion, in myth ", " SELENE"], "39": ["Feign ", " PRETEND"], "41": ["Artist Gerhard whose portraits of the Baader-Meinhof group inspired a Don DeLillo story ", " RICHTER"], "42": ["That, in Spanish ", " ESO"], "43": ["Buck's longtime bandmate ", " STIPE"], "45": ["Like the emoji ", " KISSY"], "46": ["Five-time U.S. Presidential candidate in the early nineteen-hundreds ", " DEBS"], "48": ["Those not of the cloth ", " LAICS"], "50": ["Prepubescent phase, in Freudian theory ", " LATENCYPERIOD"], "57": ["Windblown ", " AEOLIAN"], "59": ["Available for reference ", " CITABLE"], "60": ["Erstwhile HBO drama set in suburban Salt Lake City ", " BIGLOVE"], "61": ["Not cause a fuss over ", " LETRIDE"], "62": ["Contemporaries of the Pharisees ", " ESSENES"], "63": ["Device to get texts on ", " EREADER"]}, "down": {"1": ["Genealogical abbr. ", " DESC"], "2": ["Hypermeticulous ", " ANAL"], "3": ["Tangelo trademark ", " UGLI"], "4": ["Address with an apostrophe ", " MAAM"], "5": ["\"___ la Douce\" (1963 Shirley MacLaine title role) ", " IRMA"], "6": ["Head of Hollywood ", " EDITH"], "7": ["Assigns a new ranking to ", " RESEEDS"], "8": ["Provocation from a competitor ", " TOPTHAT"], "9": ["Words after an interruption ", " WHEREWASI"], "10": ["Morales of \"NYPD Blue\" ", " ESAI"], "11": ["Philosopher who wrote, \"Where there is no property, there is no injustice\" ", " LOCKE"], "12": ["The Oculus Rift and the HTC Vive, for two ", " VRHEADSETS"], "13": ["\"Death closes all: but something ___ the end / Some work of noble note, may yet be done\": \"Ulysses\" ", " ERE"], "14": ["Part of G.P.S.: Abbr. ", " SYS"], "20": ["Lat. or Lith., once ", " SSR"], "23": ["Gets the gang back together ", " REUNES"], "24": ["Tissuelike ", " PAPERY"], "25": ["Frolicked ", " ROMPED"], "26": ["Few and far between ", " SPARSE"], "27": ["Ways to make oneself content? ", " VIDEOBLOGS"], "28": ["\"The priest of the invisible,\" per Wallace Stevens ", " POET"], "29": ["Beans and greens, e.g. ", " SIDES"], "31": ["Tiny bit ", " SPECK"], "34": ["\"Wait!\" ", " DONTLEAVE"], "36": ["K-12, in ed-speak ", " ELHI"], "40": ["Feinstein and Wiest, for two ", " DIANNES"], "41": ["Make a quilt out of baby clothes, say ", " RECYCLE"], "44": ["Quick shot? ", " PIC"], "47": ["La ___ (Catholic university in Philadelphia) ", " SALLE"], "49": ["One who snoops ", " SPIER"], "51": ["Noun-forming suffix ", " TION"], "52": ["Kitchen extension? ", " ETTE"], "53": ["___ avis ", " RARA"], "54": ["[See above] ", " IBID"], "55": ["Like some shoppes ", " OLDE"], "56": ["Natty Bumppo's quarry, per the last of James Fenimore Cooper's Leatherstocking Tales ", " DEER"], "57": ["Former Japanese P.M. Shinzo ", " ABE"], "58": ["_Wasser_ , in the winter ", " EIS"]}}, "grid": [[["1", "D"], ["2", "A"], ["3", "U"], ["4", "M"], ["5", "I"], ["6", "E"], ["7", "R"], "BLACK", ["8", "T"], ["9", "W"], ["10", "E"], ["11", "L"], ["12", "V"], ["13", "E"], ["14", "S"]], [["15", "E"], ["", "N"], ["", "G"], ["", "A"], ["", "R"], ["", "D"], ["", "E"], "BLACK", ["16", "O"], ["", "H"], ["", "S"], ["", "O"], ["", "R"], ["", "R"], ["", "Y"]], [["17", "S"], ["", "A"], ["", "L"], ["", "A"], ["", "M"], ["", "I"], ["", "S"], "BLACK", ["18", "P"], ["", "E"], ["", "A"], ["", "C"], ["", "H"], ["", "E"], ["", "S"]], [["19", "C"], ["", "L"], ["", "I"], ["", "M"], ["", "A"], ["", "T"], ["", "E"], ["20", "S"], ["", "T"], ["", "R"], ["", "I"], ["", "K"], ["", "E"], "BLACK", "BLACK"], ["BLACK", "BLACK", "BLACK", "BLACK", "BLACK", ["21", "H"], ["", "E"], ["", "S"], ["", "H"], ["", "E"], "BLACK", ["22", "E"], ["", "A"], ["23", "R"], ["24", "P"]], [["25", "R"], ["26", "S"], ["27", "V"], ["28", "P"], ["29", "S"], "BLACK", ["30", "D"], ["", "R"], ["", "A"], ["", "W"], ["31", "S"], "BLACK", ["32", "D"], ["", "E"], ["", "A"]], [["33", "O"], ["", "P"], ["", "I"], ["", "O"], ["", "I"], ["34", "D"], ["", "S"], "BLACK", ["35", "T"], ["", "A"], ["", "P"], ["36", "E"], ["", "S"], ["", "U"], ["", "P"]], [["37", "M"], ["", "A"], ["", "D"], ["", "E"], ["", "D"], ["", "O"], "BLACK", "BLACK", "BLACK", ["38", "S"], ["", "E"], ["", "L"], ["", "E"], ["", "N"], ["", "E"]], [["39", "P"], ["", "R"], ["", "E"], ["", "T"], ["", "E"], ["", "N"], ["40", "D"], "BLACK", ["41", "R"], ["", "I"], ["", "C"], ["", "H"], ["", "T"], ["", "E"], ["", "R"]], [["42", "E"], ["", "S"], ["", "O"], "BLACK", ["43", "S"], ["", "T"], ["", "I"], ["44", "P"], ["", "E"], "BLACK", ["45", "K"], ["", "I"], ["", "S"], ["", "S"], ["", "Y"]], [["46", "D"], ["", "E"], ["", "B"], ["47", "S"], "BLACK", ["48", "L"], ["", "A"], ["", "I"], ["", "C"], ["49", "S"], "BLACK", "BLACK", "BLACK", "BLACK", "BLACK"], ["BLACK", "BLACK", ["50", "L"], ["", "A"], ["51", "T"], ["", "E"], ["", "N"], ["", "C"], ["", "Y"], ["", "P"], ["52", "E"], ["53", "R"], ["54", "I"], ["55", "O"], ["56", "D"]], [["57", "A"], ["58", "E"], ["", "O"], ["", "L"], ["", "I"], ["", "A"], ["", "N"], "BLACK", ["59", "C"], ["", "I"], ["", "T"], ["", "A"], ["", "B"], ["", "L"], ["", "E"]], [["60", "B"], ["", "I"], ["", "G"], ["", "L"], ["", "O"], ["", "V"], ["", "E"], "BLACK", ["61", "L"], ["", "E"], ["", "T"], ["", "R"], ["", "I"], ["", "D"], ["", "E"]], [["62", "E"], ["", "S"], ["", "S"], ["", "E"], ["", "N"], ["", "E"], ["", "S"], "BLACK", ["63", "E"], ["", "R"], ["", "E"], ["", "A"], ["", "D"], ["", "E"], ["", "R"]]]}