{"metadata": {"date": null, "rows": 15, "cols": 15}, "clues": {"across": {"1": ["Tablet on a bedside table, perhaps ", " IPAD"], "5": ["Employs the triplet flow, say ", " RAPS"], "9": ["\"Her Body and Other Parties\" author Carmen ___ Machado ", " MARIA"], "14": ["References ", " ALLUDESTO"], "16": ["Tools sometimes called counting frames ", " ABACI"], "17": ["Denomination founded by John Wesley ", " METHODISM"], "18": ["Thick smoke? ", " CIGAR"], "19": ["Chinese steamed bun ", " BAO"], "20": ["More crackers ", " MADDER"], "22": ["\"___ _pis_!\" (\"Too bad!,\" in Toulouse) ", " TANT"], "23": ["Venom ", " BILE"], "24": ["First name in a 1973 David Bowie hit ", " TOM"], "26": ["Second Avenue Subway org. ", " MTA"], "27": ["Bread in Southern cuisine ", " PONE"], "28": ["They provide partial coverage ", " AREARUGS"], "30": ["Dress-for-success accessory ", " POWERTIE"], "32": ["\"A Journal of the Plague Year\" novelist ", " DEFOE"], "33": ["He voiced Scar in 2019's \"The Lion King\" ", " CHIWETELEJIOFOR"], "35": ["Word with roll or code ", " HONOR"], "36": ["Dick Cheney's successor as Secretary of Defense ", " LESASPIN"], "37": ["Picked up ", " ANSWERED"], "39": ["\"Raising Arizona\" director ", " COEN"], "40": ["Capital of Poland? ", " PEE"], "41": ["Trygve's successor as Secretary-General of the United Nations ", " DAG"], "42": ["Didi of \"Grease\" ", " CONN"], "43": ["Variety-show lineup ", " ACTS"], "45": ["Queen in the Iliad ", " HECUBA"], "47": ["Back ", " AGO"], "50": ["\"Magic Mike\" star ", " TATUM"], "52": ["1940 novel with the line \"We black and they white. They got things and we ain't. They do things and we can't. It's just like livin' in jail\" ", " NATIVESON"], "54": ["\"O.K., so . . . that didn't happen\" ", " ILIED"], "55": ["Stop order? ", " ITINERARY"], "56": ["Blinds, essentially ", " SLATS"], "57": ["Hornswoggles ", " CONS"], "58": ["Tip-top ", " APEX"]}, "down": {"1": ["Unit for Shane McCrae or Ellen Bryant Voigt ", " IAMB"], "2": ["Kind of deal targeted by criminal-justice advocacy ", " PLEA"], "3": ["Gladys Knight or Tina Turner ", " ALTO"], "4": ["\"Oof, yeah\" ", " DUH"], "5": ["What a Klaxon might indicate ", " REDALERT"], "6": ["Digression ", " ASIDE"], "7": ["Psychological condition that may be treated with MDMA ", " PTSD"], "8": ["D\u00e9but John Ashbery collection that includes the poems \"The Grapevine\" and \"Album Leaf\" ", " SOMETREES"], "9": ["Fella ", " MAC"], "10": ["Not much ", " ABIT"], "11": ["Tatterdemalion ", " RAGAMUFFIN"], "12": ["\"That's it!\" ", " ICANTGOON"], "13": ["High-voltage weapon ", " AIRTASER"], "15": ["Pushed around ", " DOMINEERED"], "21": ["Landmark 1973 case, informally ", " ROE"], "23": ["Rapper whose album \"Unleashed\" was his first after dropping \"Lil'\" from his stage name ", " BOWWOW"], "25": ["Ad space? ", " MADISONAVE"], "27": ["Leaves for the holidays? ", " POINSETTIA"], "28": ["Troubled ", " AILED"], "29": ["Hot-button verb in the COVID-19 era ", " REOPEN"], "30": ["Dinnertime annoyance ", " PHONECALL"], "31": ["Like many anchors ", " TELEGENIC"], "33": ["Indian flatbreads made with _atta_ ", " CHAPATIS"], "34": ["\"The Black ___,\" C. L. R. James book about participants in the Haitian Revolution ", " JACOBINS"], "38": ["Fan noise ", " RAH"], "42": ["Spoil one-on-one time on \"The Bachelorette,\" say ", " CUTIN"], "44": ["Feeder filler ", " SUET"], "46": ["Ancient Roman known as the Censor ", " CATO"], "47": ["Right away ", " ASAP"], "48": ["Bloodshed ", " GORE"], "49": ["Jet ", " ONYX"], "51": ["Many OBs and E.N.T.s ", " MDS"], "53": ["Stat for Jennie Finch or Cat Osterman ", " ERA"]}}, "grid": [[["1", "I"], ["2", "P"], ["3", "A"], ["4", "D"], "BLACK", ["5", "R"], ["6", "A"], ["7", "P"], ["8", "S"], "BLACK", ["9", "M"], ["10", "A"], ["11", "R"], ["12", "I"], ["13", "A"]], [["14", "A"], ["", "L"], ["", "L"], ["", "U"], ["15", "D"], ["", "E"], ["", "S"], ["", "T"], ["", "O"], "BLACK", ["16", "A"], ["", "B"], ["", "A"], ["", "C"], ["", "I"]], [["17", "M"], ["", "E"], ["", "T"], ["", "H"], ["", "O"], ["", "D"], ["", "I"], ["", "S"], ["", "M"], "BLACK", ["18", "C"], ["", "I"], ["", "G"], ["", "A"], ["", "R"]], [["19", "B"], ["", "A"], ["", "O"], "BLACK", ["20", "M"], ["", "A"], ["", "D"], ["", "D"], ["", "E"], ["21", "R"], "BLACK", ["22", "T"], ["", "A"], ["", "N"], ["", "T"]], ["BLACK", "BLACK", "BLACK", ["23", "B"], ["", "I"], ["", "L"], ["", "E"], "BLACK", ["24", "T"], ["", "O"], ["25", "M"], "BLACK", ["26", "M"], ["", "T"], ["", "A"]], ["BLACK", "BLACK", ["27", "P"], ["", "O"], ["", "N"], ["", "E"], "BLACK", ["28", "A"], ["", "R"], ["", "E"], ["", "A"], ["29", "R"], ["", "U"], ["", "G"], ["", "S"]], ["BLACK", ["30", "P"], ["", "O"], ["", "W"], ["", "E"], ["", "R"], ["31", "T"], ["", "I"], ["", "E"], "BLACK", ["32", "D"], ["", "E"], ["", "F"], ["", "O"], ["", "E"]], [["33", "C"], ["", "H"], ["", "I"], ["", "W"], ["", "E"], ["", "T"], ["", "E"], ["", "L"], ["", "E"], ["34", "J"], ["", "I"], ["", "O"], ["", "F"], ["", "O"], ["", "R"]], [["35", "H"], ["", "O"], ["", "N"], ["", "O"], ["", "R"], "BLACK", ["36", "L"], ["", "E"], ["", "S"], ["", "A"], ["", "S"], ["", "P"], ["", "I"], ["", "N"], "BLACK"], [["37", "A"], ["", "N"], ["", "S"], ["", "W"], ["", "E"], ["38", "R"], ["", "E"], ["", "D"], "BLACK", ["39", "C"], ["", "O"], ["", "E"], ["", "N"], "BLACK", "BLACK"], [["40", "P"], ["", "E"], ["", "E"], "BLACK", ["41", "D"], ["", "A"], ["", "G"], "BLACK", ["42", "C"], ["", "O"], ["", "N"], ["", "N"], "BLACK", "BLACK", "BLACK"], [["43", "A"], ["", "C"], ["", "T"], ["44", "S"], "BLACK", ["45", "H"], ["", "E"], ["46", "C"], ["", "U"], ["", "B"], ["", "A"], "BLACK", ["47", "A"], ["48", "G"], ["49", "O"]], [["50", "T"], ["", "A"], ["", "T"], ["", "U"], ["51", "M"], "BLACK", ["52", "N"], ["", "A"], ["", "T"], ["", "I"], ["", "V"], ["53", "E"], ["", "S"], ["", "O"], ["", "N"]], [["54", "I"], ["", "L"], ["", "I"], ["", "E"], ["", "D"], "BLACK", ["55", "I"], ["", "T"], ["", "I"], ["", "N"], ["", "E"], ["", "R"], ["", "A"], ["", "R"], ["", "Y"]], [["56", "S"], ["", "L"], ["", "A"], ["", "T"], ["", "S"], "BLACK", ["57", "C"], ["", "O"], ["", "N"], ["", "S"], "BLACK", ["58", "A"], ["", "P"], ["", "E"], ["", "X"]]]}