{"metadata": {"date": null, "rows": 15, "cols": 15}, "clues": {"across": {"1": ["Uno card that causes a player to lose a turn ", " SKIP"], "5": ["Scatter (about) ", " STREW"], "10": ["Vivacity ", " BRIO"], "14": ["\"West Coast\" singer Del Rey ", " LANA"], "15": ["\"Tonight's no good for me\" ", " IHAVEPLANS"], "17": ["___ Pro (computer discontinued in 2021) ", " IMAC"], "18": ["Targets ", " TAKESAIMAT"], "19": ["Have a chat ", " TALK"], "20": ["Number of points earned by the best possible cribbage hand ", " TWENTYNINE"], "21": ["Gives lip to ", " SASSES"], "23": ["Western : oater :: soap opera : ___ ", " SUDSER"], "24": ["Evil C.E.O. of LexCorp ", " LUTHOR"], "25": ["Weapon for Indiana Jones ", " WHIP"], "27": ["Survey choice listed last ", " OTHER"], "28": ["Hitting-the-ground sound ", " THUD"], "29": ["Picket-line crosser ", " SCAB"], "33": ["Typical kaiju film ", " CREATUREFEATURE"], "36": ["Mario ___ (racing-game series) ", " KART"], "37": ["Bakery purchase ", " LOAF"], "38": ["Mailer attachment ", " LABEL"], "39": ["Miranda or Jane, to Rebecca, in \"Rebecca of Sunnybrook Farm\" ", " AUNT"], "40": ["Spread out ", " SPRAWL"], "41": ["Subject of a 2021 California special election ", " RECALL"], "45": ["Noise from a hedgerow ", " RUSTLE"], "46": ["Suppliers of snark ", " SMARTASSES"], "49": ["Resigned reaction ", " SIGH"], "51": ["Cursed items in \"The Ring\" ", " VIDEOTAPES"], "52": ["Slender woodwind ", " OBOE"], "53": ["Standing order? ", " PLEASERISE"], "54": ["Gift-tag word ", " FROM"], "55": ["Back-lot constructions ", " SETS"], "56": ["Vicks decongestant spray ", " SINEX"], "57": ["Operation Varsity Blues investigators, informally ", " FEDS"]}, "down": {"1": ["Open with a letter opener ", " SLIT"], "2": ["Sex work? ", " KAMASUTRA"], "3": ["Highly agitated ", " INALATHER"], "4": ["Carries a gun, colloquially ", " PACKSHEAT"], "5": ["Date-night hire ", " SITTER"], "6": ["Defrosts ", " THAWS"], "7": ["Gather on the lawn? ", " RAKE"], "8": ["Fairly matched ", " EVEN"], "9": ["Where Hell's Kitchen is ", " WESTSIDE"], "10": ["Like some taste tests ", " BLIND"], "11": ["\"Groundhog Day\" director Harold ", " RAMIS"], "12": ["Harebrained ", " INANE"], "13": ["Brand that makes Beehive Blenders ", " OSTER"], "16": ["Creditor's demand ", " PAYUP"], "22": ["Organize into piles, say ", " SORT"], "24": ["Symbol on a key-fob button ", " LOCK"], "25": ["Gluten source ", " WHEAT"], "26": ["Peevish mood ", " HUFF"], "28": ["1982 arcade game, or the film it was based on ", " TRON"], "29": ["Gets the ball rolling ", " STARTSOFF"], "30": ["Rum and Coke, by another name ", " CUBALIBRE"], "31": ["\"No hard feelings, right?\" ", " AREWEGOOD"], "32": ["Swinger in a church tower ", " BELL"], "34": ["Delivers a warbling wail ", " ULULATES"], "35": ["The Matterhorn's range ", " ALPS"], "39": ["Boys'-choir voices ", " ALTOS"], "40": ["English county where the Battle of Hastings was fought ", " SUSSEX"], "41": ["Says yea or nay in re: a soir\u00e9e, say ", " RSVPS"], "42": ["\"Once Upon a Time . . . in Hollywood\" actor Hirsch ", " EMILE"], "43": ["West Pointer, e.g. ", " CADET"], "44": ["Polygon calculations ", " AREAS"], "45": ["Witherspoon of \"Wild\" ", " REESE"], "47": ["Bengali bridal garment ", " SARI"], "48": ["\"Wheel of Fortune\" option ", " SPIN"], "50": ["Clothing industry's bottom lines? ", " HEMS"]}}, "grid": [[["1", "S"], ["2", "K"], ["3", "I"], ["4", "P"], "BLACK", ["5", "S"], ["6", "T"], ["7", "R"], ["8", "E"], ["9", "W"], "BLACK", ["10", "B"], ["11", "R"], ["12", "I"], ["13", "O"]], [["14", "L"], ["", "A"], ["", "N"], ["", "A"], "BLACK", ["15", "I"], ["", "H"], ["", "A"], ["", "V"], ["", "E"], ["16", "P"], ["", "L"], ["", "A"], ["", "N"], ["", "S"]], [["17", "I"], ["", "M"], ["", "A"], ["", "C"], "BLACK", ["18", "T"], ["", "A"], ["", "K"], ["", "E"], ["", "S"], ["", "A"], ["", "I"], ["", "M"], ["", "A"], ["", "T"]], [["19", "T"], ["", "A"], ["", "L"], ["", "K"], "BLACK", ["20", "T"], ["", "W"], ["", "E"], ["", "N"], ["", "T"], ["", "Y"], ["", "N"], ["", "I"], ["", "N"], ["", "E"]], ["BLACK", ["21", "S"], ["", "A"], ["", "S"], ["22", "S"], ["", "E"], ["", "S"], "BLACK", "BLACK", ["23", "S"], ["", "U"], ["", "D"], ["", "S"], ["", "E"], ["", "R"]], [["24", "L"], ["", "U"], ["", "T"], ["", "H"], ["", "O"], ["", "R"], "BLACK", ["25", "W"], ["26", "H"], ["", "I"], ["", "P"], "BLACK", "BLACK", "BLACK", "BLACK"], [["27", "O"], ["", "T"], ["", "H"], ["", "E"], ["", "R"], "BLACK", ["28", "T"], ["", "H"], ["", "U"], ["", "D"], "BLACK", ["29", "S"], ["30", "C"], ["31", "A"], ["32", "B"]], [["33", "C"], ["", "R"], ["", "E"], ["", "A"], ["", "T"], ["34", "U"], ["", "R"], ["", "E"], ["", "F"], ["", "E"], ["35", "A"], ["", "T"], ["", "U"], ["", "R"], ["", "E"]], [["36", "K"], ["", "A"], ["", "R"], ["", "T"], "BLACK", ["37", "L"], ["", "O"], ["", "A"], ["", "F"], "BLACK", ["38", "L"], ["", "A"], ["", "B"], ["", "E"], ["", "L"]], ["BLACK", "BLACK", "BLACK", "BLACK", ["39", "A"], ["", "U"], ["", "N"], ["", "T"], "BLACK", ["40", "S"], ["", "P"], ["", "R"], ["", "A"], ["", "W"], ["", "L"]], [["41", "R"], ["42", "E"], ["43", "C"], ["44", "A"], ["", "L"], ["", "L"], "BLACK", "BLACK", ["45", "R"], ["", "U"], ["", "S"], ["", "T"], ["", "L"], ["", "E"], "BLACK"], [["46", "S"], ["", "M"], ["", "A"], ["", "R"], ["", "T"], ["", "A"], ["47", "S"], ["48", "S"], ["", "E"], ["", "S"], "BLACK", ["49", "S"], ["", "I"], ["", "G"], ["50", "H"]], [["51", "V"], ["", "I"], ["", "D"], ["", "E"], ["", "O"], ["", "T"], ["", "A"], ["", "P"], ["", "E"], ["", "S"], "BLACK", ["52", "O"], ["", "B"], ["", "O"], ["", "E"]], [["53", "P"], ["", "L"], ["", "E"], ["", "A"], ["", "S"], ["", "E"], ["", "R"], ["", "I"], ["", "S"], ["", "E"], "BLACK", ["54", "F"], ["", "R"], ["", "O"], ["", "M"]], [["55", "S"], ["", "E"], ["", "T"], ["", "S"], "BLACK", ["56", "S"], ["", "I"], ["", "N"], ["", "E"], ["", "X"], "BLACK", ["57", "F"], ["", "E"], ["", "D"], ["", "S"]]]}