{"metadata": {"date": null, "rows": 15, "cols": 15}, "clues": {"across": {"1": ["Performed at a jazz club, say ", " GIGGED"], "7": ["Voice disapproval of ", " HISSAT"], "13": ["Agcy. with the slogan \"Building peace in the minds of men and women\" ", " UNESCO"], "14": ["Merchant of music? ", " NATALIE"], "15": ["Common wine-label word ", " ESTATE"], "16": ["1957 Marlon Brando film, for which Miyoshi Umeki won a best-supporting-actress Oscar ", " SAYONARA"], "17": ["Hi-___ audio player ", " RES"], "18": ["\"An ___\" (1941 O'Keeffe pastel) ", " ORCHID"], "20": ["Ombr\u00e9 expert ", " DYER"], "21": ["Hammock breaks ", " NAPS"], "23": ["Hairless, now ", " SHORN"], "24": ["Parisian demonstrative ", " CES"], "25": ["Half brother of Ishmael ", " ISAAC"], "27": ["Former Bolivian President Morales ", " EVO"], "28": ["Album between \"Thriller\" and \"Dangerous\" ", " BAD"], "29": ["Accepting quarters, for short ", " COINOP"], "31": ["Some emo-influenced TikTokers ", " EBOYS"], "33": ["Forthcoming TV reboot starring Sarah Jessica Parker as Carrie Bradshaw ", " ANDJUSTLIKETHAT"], "38": ["Absolute ", " UTTER"], "39": ["She danced to get a head ", " SALOME"], "40": ["\"Don't think so!\" ", " NAH"], "41": ["\"Read Across America\" org. ", " NEA"], "43": ["What type-A types rarely do ", " RELAX"], "44": ["Chemist's study ", " ION"], "45": ["Chryslers of the eighties ", " KCARS"], "47": ["Evening, in Tuscany ", " SERA"], "48": ["Part of a foot ", " INCH"], "49": ["Conifer found in Yosemite National Park ", " REDFIR"], "51": ["___ Racist (alternative-rap trio that broke up in 2012) ", " DAS"], "52": ["Ex amount? ", " PALIMONY"], "54": ["Company where the chemist Stephanie Kwolek developed Kevlar ", " DUPONT"], "56": ["Lush ", " OPULENT"], "57": ["Esteem ", " REPUTE"], "58": ["\"___ by Starlight\" (standard on the Miles Davis album \"Jazz Track\") ", " STELLA"], "59": ["\"Chain of Fools\" singer, familiarly ", " ARETHA"]}, "down": {"1": ["1937 antiwar masterwork by Picasso ", " GUERNICA"], "2": ["Like produce at a farmers' market ", " INSEASON"], "3": ["Makes bread? ", " GETSPAID"], "4": ["Fed. property manager ", " GSA"], "5": ["Start to morph? ", " ECTO"], "6": ["Busy bodies? ", " DOERS"], "7": ["Composer known as the father of the string quartet ", " HAYDN"], "8": ["Runner-up to Yamaguchi at the 1992 Winter Olympics ", " ITO"], "9": ["Coastal constructions ", " SANDCASTLES"], "10": ["Nailed a comedy routine ", " SLAYED"], "11": ["Half of a South American capital ", " AIRES"], "12": ["Sign of joy or sorrow ", " TEAR"], "14": ["World capital with minibuses called _matatus_ ", " NAIROBI"], "16": ["Descriptor for construction projects that are set to go and awaiting funding ", " SHOVELREADY"], "19": ["Antonio Banderas role of 1996 ", " CHE"], "22": ["Site of a key battle of the Spanish-American War ", " SANJUANHILL"], "26": ["Sophisticated ", " COUTH"], "28": ["How some play the piano ", " BYEAR"], "30": ["Calif. setting ", " PST"], "32": ["Letters of consent? ", " OKS"], "34": ["Chinese tech company whose valuation is trillions of times more than its name suggests ", " TENCENT"], "35": ["Made a putt ", " HOLEDOUT"], "36": ["Flower admired by a rose for its longevity, in an Aesop fable ", " AMARANTH"], "37": ["Black gold ", " TEXASTEA"], "40": ["\"Darned if I know\" ", " NOCLUE"], "42": ["\"Do you want a treat?\" response ", " ARF"], "44": ["Incongruous ", " INAPT"], "45": ["Capital of Sweden ", " KRONA"], "46": ["Gulf of ___ (body of water off the coast of Libya) ", " SIDRA"], "48": ["2013 events for Twitter and RetailMeNot, in brief ", " IPOS"], "50": ["Contrite one ", " RUER"], "53": ["First name shared by two Spice Girls ", " MEL"], "55": ["Safety gear for I.C.U. workers ", " PPE"]}}, "grid": [[["1", "G"], ["2", "I"], ["3", "G"], ["4", "G"], ["5", "E"], ["6", "D"], "BLACK", "BLACK", "BLACK", ["7", "H"], ["8", "I"], ["9", "S"], ["10", "S"], ["11", "A"], ["12", "T"]], [["13", "U"], ["", "N"], ["", "E"], ["", "S"], ["", "C"], ["", "O"], "BLACK", "BLACK", ["14", "N"], ["", "A"], ["", "T"], ["", "A"], ["", "L"], ["", "I"], ["", "E"]], [["15", "E"], ["", "S"], ["", "T"], ["", "A"], ["", "T"], ["", "E"], "BLACK", ["16", "S"], ["", "A"], ["", "Y"], ["", "O"], ["", "N"], ["", "A"], ["", "R"], ["", "A"]], [["17", "R"], ["", "E"], ["", "S"], "BLACK", ["18", "O"], ["", "R"], ["19", "C"], ["", "H"], ["", "I"], ["", "D"], "BLACK", ["20", "D"], ["", "Y"], ["", "E"], ["", "R"]], [["21", "N"], ["", "A"], ["", "P"], ["22", "S"], "BLACK", ["23", "S"], ["", "H"], ["", "O"], ["", "R"], ["", "N"], "BLACK", ["24", "C"], ["", "E"], ["", "S"], "BLACK"], [["25", "I"], ["", "S"], ["", "A"], ["", "A"], ["26", "C"], "BLACK", ["27", "E"], ["", "V"], ["", "O"], "BLACK", ["28", "B"], ["", "A"], ["", "D"], "BLACK", "BLACK"], [["29", "C"], ["", "O"], ["", "I"], ["", "N"], ["", "O"], ["30", "P"], "BLACK", ["31", "E"], ["", "B"], ["32", "O"], ["", "Y"], ["", "S"], "BLACK", "BLACK", "BLACK"], [["33", "A"], ["", "N"], ["", "D"], ["", "J"], ["", "U"], ["", "S"], ["34", "T"], ["", "L"], ["", "I"], ["", "K"], ["", "E"], ["", "T"], ["35", "H"], ["36", "A"], ["37", "T"]], ["BLACK", "BLACK", "BLACK", ["38", "U"], ["", "T"], ["", "T"], ["", "E"], ["", "R"], "BLACK", ["39", "S"], ["", "A"], ["", "L"], ["", "O"], ["", "M"], ["", "E"]], ["BLACK", "BLACK", ["40", "N"], ["", "A"], ["", "H"], "BLACK", ["41", "N"], ["", "E"], ["42", "A"], "BLACK", ["43", "R"], ["", "E"], ["", "L"], ["", "A"], ["", "X"]], ["BLACK", ["44", "I"], ["", "O"], ["", "N"], "BLACK", ["45", "K"], ["", "C"], ["", "A"], ["", "R"], ["46", "S"], "BLACK", ["47", "S"], ["", "E"], ["", "R"], ["", "A"]], [["48", "I"], ["", "N"], ["", "C"], ["", "H"], "BLACK", ["49", "R"], ["", "E"], ["", "D"], ["", "F"], ["", "I"], ["50", "R"], "BLACK", ["51", "D"], ["", "A"], ["", "S"]], [["52", "P"], ["", "A"], ["", "L"], ["", "I"], ["53", "M"], ["", "O"], ["", "N"], ["", "Y"], "BLACK", ["54", "D"], ["", "U"], ["55", "P"], ["", "O"], ["", "N"], ["", "T"]], [["56", "O"], ["", "P"], ["", "U"], ["", "L"], ["", "E"], ["", "N"], ["", "T"], "BLACK", "BLACK", ["57", "R"], ["", "E"], ["", "P"], ["", "U"], ["", "T"], ["", "E"]], [["58", "S"], ["", "T"], ["", "E"], ["", "L"], ["", "L"], ["", "A"], "BLACK", "BLACK", "BLACK", ["59", "A"], ["", "R"], ["", "E"], ["", "T"], ["", "H"], ["", "A"]]]}