{"metadata": {"date": null, "rows": 15, "cols": 15}, "clues": {"across": {"1": ["Predicted post-pandemic upsurge in globe-trotting ", " TRAVELBOOM"], "11": ["U.S. Navy officer ", " ENS"], "14": ["Preacher of the Second Great Awakening, say ", " REVIVALIST"], "15": ["Toss, as a coin ", " FLIP"], "16": ["Kalamata-dotted breads ", " OLIVEROLLS"], "17": ["\"Seven Beauties\" director Wertm\u00fcller ", " LINA"], "18": ["Start to function? ", " DYS"], "19": ["Bonkers ", " NUTSO"], "20": ["\"Harold and ___ Go to White Castle\" (2004 comedy) ", " KUMAR"], "21": ["Uintah and Ouray Reservation residents ", " UTES"], "22": ["Certain creator of a toxic work environment ", " SEXIST"], "23": ["Grassy clumps ", " TUFTS"], "26": ["Type of field or mining ", " DATA"], "28": ["Peeples of \"Pretty Little Liars\" ", " NIA"], "29": ["___ B'rith ", " BNAI"], "30": ["Mascot with the catchphrase \"Follow your nose\" ", " TOUCANSAM"], "33": ["Step-by-step guide? ", " DANCEINSTRUCTOR"], "36": ["They're often seen hanging around pubs ", " PLASMATVS"], "37": ["Wine: combining form ", " OENO"], "38": ["Hosp. workers' gear that may include safety glasses and respirators ", " PPE"], "39": ["Some bills ", " TENS"], "40": ["Cleared, as tables ", " BUSED"], "41": ["More boho-inspired, say ", " ARTIER"], "43": ["Skier's transport ", " TBAR"], "45": ["\"Heck if I know!\" ", " GOTME"], "46": ["\"The L Word\" actress Pam ", " GRIER"], "48": ["Inspiring leader? ", " AWE"], "51": ["\"Three Places in New England\" composer Charles ", " IVES"], "52": ["Areas with low COVID-19 infection rates, per some classification systems ", " GREENZONES"], "54": ["Nephew of Caligula ", " NERO"], "55": ["Sweet, aromatic bourbon cocktails ", " MINTJULEPS"], "56": ["Dept.-store wares ", " GDS"], "57": ["Legendary performer/director Perry, for whom Broadway's highest honors are named ", " ANTOINETTE"]}, "down": {"1": ["Walked over ", " TROD"], "2": ["Depend ", " RELY"], "3": ["Bird, to 54-Across ", " AVIS"], "4": ["Palindromic pal on \"The Lucy Show\" ", " VIV"], "5": ["Happenings ", " EVENTS"], "6": ["Movie cowboy Lash ", " LARUE"], "7": ["Ink stains ", " BLOTS"], "8": ["Fryolator fillers ", " OILS"], "9": ["Where Henrik Ibsen is buried ", " OSLO"], "10": ["Peaks, for short ", " MTS"], "11": ["Knocks out of contention ", " ELIMINATES"], "12": ["\"To Be Young, Gifted and Black\" singer nicknamed the High Priestess of Soul ", " NINASIMONE"], "13": ["Old rival of Athens ", " SPARTA"], "15": ["Continuous change ", " FLUX"], "20": ["Portrayer of Neo in \"The Matrix\" ", " KEANU"], "21": ["City near Rome, New York ", " UTICA"], "22": ["Milky Way contents ", " STARS"], "23": ["\"Still mulling it over,\" on a sched. ", " TBD"], "24": ["Not fit for publication, like spammy blog comments ", " UNAPPROVED"], "25": ["Praiseful compositions ", " FANLETTERS"], "26": ["Uses a cleaning cloth ", " DUSTS"], "27": ["Final segment of \"The Tempest\" ", " ACTV"], "30": ["Buzzing kitchen gadget ", " TIMER"], "31": ["Take ___ empty stomach ", " ONAN"], "32": ["Really scrub, as a tub ", " SCOUR"], "34": ["Cosmetics executive Lauder ", " ESTEE"], "35": ["Baseball Hall of Famer Carew ", " ROD"], "38": ["Contacting via beeper ", " PAGING"], "40": ["\"From Dawn to Decadence\" author Jacques ", " BARZUN"], "42": ["\"___ proud!\" (kveller's cry) ", " IMSO"], "43": ["Link with ", " TIETO"], "44": ["Protagonist of Colson Whitehead's \"Sag Harbor\" ", " BENJI"], "46": ["Toothy smile ", " GRIN"], "47": ["Flat fee? ", " RENT"], "48": ["Work without ___ (take risks) ", " ANET"], "49": ["Cried a river ", " WEPT"], "50": ["To be, to Brutus ", " ESSE"], "52": ["\"Today\" rival, for short ", " GMA"], "53": ["Flamenco enthusiast's cheer ", " OLE"]}}, "grid": [[["1", "T"], ["2", "R"], ["3", "A"], ["4", "V"], ["5", "E"], ["6", "L"], ["7", "B"], ["8", "O"], ["9", "O"], ["10", "M"], "BLACK", "BLACK", ["11", "E"], ["12", "N"], ["13", "S"]], [["14", "R"], ["", "E"], ["", "V"], ["", "I"], ["", "V"], ["", "A"], ["", "L"], ["", "I"], ["", "S"], ["", "T"], "BLACK", ["15", "F"], ["", "L"], ["", "I"], ["", "P"]], [["16", "O"], ["", "L"], ["", "I"], ["", "V"], ["", "E"], ["", "R"], ["", "O"], ["", "L"], ["", "L"], ["", "S"], "BLACK", ["17", "L"], ["", "I"], ["", "N"], ["", "A"]], [["18", "D"], ["", "Y"], ["", "S"], "BLACK", ["19", "N"], ["", "U"], ["", "T"], ["", "S"], ["", "O"], "BLACK", ["20", "K"], ["", "U"], ["", "M"], ["", "A"], ["", "R"]], ["BLACK", "BLACK", "BLACK", ["21", "U"], ["", "T"], ["", "E"], ["", "S"], "BLACK", "BLACK", ["22", "S"], ["", "E"], ["", "X"], ["", "I"], ["", "S"], ["", "T"]], [["23", "T"], ["24", "U"], ["25", "F"], ["", "T"], ["", "S"], "BLACK", "BLACK", ["26", "D"], ["27", "A"], ["", "T"], ["", "A"], "BLACK", ["28", "N"], ["", "I"], ["", "A"]], [["29", "B"], ["", "N"], ["", "A"], ["", "I"], "BLACK", ["30", "T"], ["31", "O"], ["", "U"], ["", "C"], ["", "A"], ["", "N"], ["32", "S"], ["", "A"], ["", "M"], "BLACK"], [["33", "D"], ["", "A"], ["", "N"], ["", "C"], ["34", "E"], ["", "I"], ["", "N"], ["", "S"], ["", "T"], ["", "R"], ["", "U"], ["", "C"], ["", "T"], ["", "O"], ["35", "R"]], ["BLACK", ["36", "P"], ["", "L"], ["", "A"], ["", "S"], ["", "M"], ["", "A"], ["", "T"], ["", "V"], ["", "S"], "BLACK", ["37", "O"], ["", "E"], ["", "N"], ["", "O"]], [["38", "P"], ["", "P"], ["", "E"], "BLACK", ["39", "T"], ["", "E"], ["", "N"], ["", "S"], "BLACK", "BLACK", ["40", "B"], ["", "U"], ["", "S"], ["", "E"], ["", "D"]], [["41", "A"], ["", "R"], ["", "T"], ["42", "I"], ["", "E"], ["", "R"], "BLACK", "BLACK", ["43", "T"], ["44", "B"], ["", "A"], ["", "R"], "BLACK", "BLACK", "BLACK"], [["45", "G"], ["", "O"], ["", "T"], ["", "M"], ["", "E"], "BLACK", ["46", "G"], ["47", "R"], ["", "I"], ["", "E"], ["", "R"], "BLACK", ["48", "A"], ["49", "W"], ["50", "E"]], [["51", "I"], ["", "V"], ["", "E"], ["", "S"], "BLACK", ["52", "G"], ["", "R"], ["", "E"], ["", "E"], ["", "N"], ["", "Z"], ["53", "O"], ["", "N"], ["", "E"], ["", "S"]], [["54", "N"], ["", "E"], ["", "R"], ["", "O"], "BLACK", ["55", "M"], ["", "I"], ["", "N"], ["", "T"], ["", "J"], ["", "U"], ["", "L"], ["", "E"], ["", "P"], ["", "S"]], [["56", "G"], ["", "D"], ["", "S"], "BLACK", "BLACK", ["57", "A"], ["", "N"], ["", "T"], ["", "O"], ["", "I"], ["", "N"], ["", "E"], ["", "T"], ["", "T"], ["", "E"]]]}