{"metadata": {"date": null, "rows": 15, "cols": 15}, "clues": {"across": {"1": ["Don't dispute ", " AGREEWITH"], "10": ["Marconi rival financed by Morgan ", " TESLA"], "15": ["Some dough, but not much ", " BEERMONEY"], "16": ["Spent ", " ALLIN"], "17": ["Made known ", " ANNOUNCED"], "18": ["Unvarnished ", " BLUNT"], "19": ["Establishes as the standard ", " SETS"], "20": ["Whom the BBC once compared Murdoch to ", " KANE"], "21": ["Advances ", " LENDS"], "22": ["Baroque or Romantic ", " ERA"], "23": ["''Be a SORE winner'' sloganeer ", " BENGAY"], "24": ["Henry Higgins oath ", " DAMN"], "26": ["Not as wholesome ", " GAMIER"], "30": ["Agile ", " LOOSELIMBED"], "33": ["Type of wooden siding ", " BATTENBOARD"], "35": ["Reproachful rhetorical question ", " HOWCOULDYOU"], "37": ["Threw into disorder ", " MESSED"], "38": ["Navajo art medium ", " SAND"], "40": ["Work in stone ", " SCULPT"], "44": ["Shake, rattle and roll ", " JAR"], "45": ["Old-time nickname for Elizabeth ", " ELSIE"], "46": ["Vegas-area watering hole ", " MEAD"], "50": ["Base for some floats ", " COLA"], "51": ["Fighting word ", " ROUND"], "52": ["Notable Ideal Toy licensor of 1979 ", " ERNORUBIK"], "54": ["Eels for meals ", " UNAGI"], "55": ["Cope with quips ", " TAKEAJOKE"], "56": ["Word from the Greek for ''apple'' ", " MELON"], "57": ["Talk host whose full first name ends in ''let'' ", " STARJONES"]}, "down": {"1": ["Brought down ", " ABASED"], "2": ["Prevailing ", " GENERAL"], "3": ["Protestors-on-call ", " RENTAMOB"], "4": ["Winged sculpture discovered at Pompeii ", " EROS"], "5": ["Tall two-legged trotter ", " EMU"], "6": ["Political nerd ", " WONK"], "7": ["Ancient potato farmer ", " INCA"], "8": ["Emerging consumer ", " TEEN"], "9": ["Name on the presidential library locale list ", " HYDE"], "10": ["Script step ", " TABLEREAD"], "11": ["Oscar winner as Alice (1975) ", " ELLEN"], "12": ["Catapulted ", " SLUNG"], "13": ["Pretty, in Mexico City ", " LINDA"], "14": ["More than a bit bothered ", " ANTSY"], "23": ["Don't restrain oneself ", " BEBOLD"], "25": ["Ancient mariner ", " NOAH"], "26": ["Shower, say ", " GETWET"], "27": ["Smart __ ", " ALECS"], "28": ["''Odyssey'' king ", " MINOS"], "29": ["Shower, say ", " IMBUE"], "31": ["Arrived with a bang ", " STOMPEDIN"], "32": ["Jazz Age abstainers ", " DRYS"], "34": ["Psych out ", " DOAJOBON"], "36": ["Dissimilar ", " UNALIKE"], "39": ["Barnyard bunch ", " DRAKES"], "40": ["Cholesterol locale ", " SERUM"], "41": ["DNA match ", " CLONE"], "42": ["Opposite of ''unexpected'' ", " USUAL"], "43": ["Legalese, for instance ", " LINGO"], "46": ["Their stadium has a Jackie Robinson Rotunda ", " METS"], "47": ["Was: Lat. ", " ERAT"], "48": ["''My Way'' autobiographer ", " ANKA"], "49": ["Perpetrator ", " DOER"], "50": ["'80s big-barker bestseller ", " CUJO"], "53": ["Dominion opposed by Gandhi ", " RAJ"]}}, "grid": [[["1", "A"], ["2", "G"], ["3", "R"], ["4", "E"], ["5", "E"], ["6", "W"], ["7", "I"], ["8", "T"], ["9", "H"], "BLACK", ["10", "T"], ["11", "E"], ["12", "S"], ["13", "L"], ["14", "A"]], [["15", "B"], ["", "E"], ["", "E"], ["", "R"], ["", "M"], ["", "O"], ["", "N"], ["", "E"], ["", "Y"], "BLACK", ["16", "A"], ["", "L"], ["", "L"], ["", "I"], ["", "N"]], [["17", "A"], ["", "N"], ["", "N"], ["", "O"], ["", "U"], ["", "N"], ["", "C"], ["", "E"], ["", "D"], "BLACK", ["18", "B"], ["", "L"], ["", "U"], ["", "N"], ["", "T"]], [["19", "S"], ["", "E"], ["", "T"], ["", "S"], "BLACK", ["20", "K"], ["", "A"], ["", "N"], ["", "E"], "BLACK", ["21", "L"], ["", "E"], ["", "N"], ["", "D"], ["", "S"]], [["22", "E"], ["", "R"], ["", "A"], "BLACK", "BLACK", "BLACK", "BLACK", "BLACK", "BLACK", ["23", "B"], ["", "E"], ["", "N"], ["", "G"], ["", "A"], ["", "Y"]], [["24", "D"], ["", "A"], ["", "M"], ["25", "N"], "BLACK", ["26", "G"], ["27", "A"], ["28", "M"], ["29", "I"], ["", "E"], ["", "R"], "BLACK", "BLACK", "BLACK", "BLACK"], ["BLACK", ["30", "L"], ["", "O"], ["", "O"], ["31", "S"], ["", "E"], ["", "L"], ["", "I"], ["", "M"], ["", "B"], ["", "E"], ["32", "D"], "BLACK", "BLACK", "BLACK"], ["BLACK", "BLACK", ["33", "B"], ["", "A"], ["", "T"], ["", "T"], ["", "E"], ["", "N"], ["", "B"], ["", "O"], ["", "A"], ["", "R"], ["34", "D"], "BLACK", "BLACK"], ["BLACK", "BLACK", "BLACK", ["35", "H"], ["", "O"], ["", "W"], ["", "C"], ["", "O"], ["", "U"], ["", "L"], ["", "D"], ["", "Y"], ["", "O"], ["36", "U"], "BLACK"], ["BLACK", "BLACK", "BLACK", "BLACK", ["37", "M"], ["", "E"], ["", "S"], ["", "S"], ["", "E"], ["", "D"], "BLACK", ["38", "S"], ["", "A"], ["", "N"], ["39", "D"]], [["40", "S"], ["41", "C"], ["42", "U"], ["43", "L"], ["", "P"], ["", "T"], "BLACK", "BLACK", "BLACK", "BLACK", "BLACK", "BLACK", ["44", "J"], ["", "A"], ["", "R"]], [["45", "E"], ["", "L"], ["", "S"], ["", "I"], ["", "E"], "BLACK", ["46", "M"], ["47", "E"], ["48", "A"], ["49", "D"], "BLACK", ["50", "C"], ["", "O"], ["", "L"], ["", "A"]], [["51", "R"], ["", "O"], ["", "U"], ["", "N"], ["", "D"], "BLACK", ["52", "E"], ["", "R"], ["", "N"], ["", "O"], ["53", "R"], ["", "U"], ["", "B"], ["", "I"], ["", "K"]], [["54", "U"], ["", "N"], ["", "A"], ["", "G"], ["", "I"], "BLACK", ["55", "T"], ["", "A"], ["", "K"], ["", "E"], ["", "A"], ["", "J"], ["", "O"], ["", "K"], ["", "E"]], [["56", "M"], ["", "E"], ["", "L"], ["", "O"], ["", "N"], "BLACK", ["57", "S"], ["", "T"], ["", "A"], ["", "R"], ["", "J"], ["", "O"], ["", "N"], ["", "E"], ["", "S"]]]}