{"metadata": {"date": null, "rows": 15, "cols": 15}, "clues": {"across": {"1": ["Improper running down ", " DEFAMATION"], "11": ["''Pass it on'' preceder ", " PSST"], "15": ["Bound to happen ", " INEXORABLE"], "16": ["It may be nursed in a nursery ", " OWIE"], "17": ["Bottoms of channels ", " STREAMBEDS"], "18": ["__ suit ", " PANT"], "19": ["Gull or rook ", " CON"], "20": ["Group of problems ", " TEST"], "21": ["Guilty feeling ", " TWINGE"], "23": ["BUZZR's cable competitor ", " GSN"], "24": ["Instrument with punched paper ", " PIANOLA"], "25": ["Unfulfilled fancy ", " HOPE"], "28": ["Volcanic creation ", " ISLAND"], "31": ["USN designation ", " RET"], "32": ["''Science is based . . . __ openness to see the universe as it really is'': Carl Sagan ", " ONAN"], "33": ["Not much ", " ATINGE"], "34": ["Ending like -ette ", " CLE"], "35": ["Left, to ''cart\u00f3grafos'' ", " OESTE"], "37": ["2020 retiree with his own ''nomics'' ", " ABE"], "38": ["Bat over ", " REHIT"], "40": ["Target of a trimming ", " FAT"], "41": ["''To be specific . . .'' ", " NAMELY"], "44": ["Teeming ", " RIFE"], "45": ["''Notes from the Backpack'' podcast grp. ", " PTA"], "46": ["Foreshadowing phrase ", " ORELSE"], "47": ["Foreshadowed day of long ago ", " IDES"], "48": ["Bowl for cr\u00e8me br\u00fbl\u00e9e ", " RAMEKIN"], "50": ["Store to improve ", " AGE"], "52": ["Patria di Pavarotti ", " ITALIA"], "53": ["Sound off ", " RAVE"], "55": ["Quick hit ", " JAB"], "58": ["Greek counterpart of Victoria ", " NIKE"], "59": ["Fiery-sounding sushi ", " DRAGONROLL"], "62": ["Some forensic accountants, for short ", " TMEN"], "63": ["What those who have had it have ", " NOPATIENCE"], "64": ["Microbiologist's creations ", " SERA"], "65": ["''Dinner is served'' sight ", " ENTREEDISH"]}, "down": {"1": ["BMW logo, e.g. ", " DISC"], "2": ["''Inner'' starter ", " ENTO"], "3": ["Green Crayola color ", " FERN"], "4": ["Hacker's need ", " AXE"], "5": ["Venerable defensive devices ", " MOATS"], "6": ["It's south of Georgia ", " ARMENIA"], "7": ["Close watch ", " TABS"], "8": ["''Puh-leeze!'' ", " IBET"], "9": ["__ hat ", " OLD"], "10": ["Up-a-tree activity ", " NESTING"], "11": ["Eat whole, as a dumpling ", " POPIN"], "12": ["Greenhouse plant with neck-shaped flowers ", " SWANORCHID"], "13": ["Free state? ", " SINGLELIFE"], "14": ["Sit-downs ", " TETEATETES"], "22": ["Wetlands visitor ", " WADER"], "23": ["Certain proper party ", " GENT"], "24": ["Quilt components ", " PANELS"], "25": ["Roof proof of a Santa visit ", " HOOFPRINTS"], "26": ["Separation exhortation ", " ONEATATIME"], "27": ["It's cranked in kitchens ", " PASTAMAKER"], "29": ["Ultimate source of hay fever symptoms ", " STAMEN"], "30": ["Particular type of 1 Across ", " LIBEL"], "36": ["Korean soup ingredient ", " ENOKI"], "39": ["Ohio's Lake __ College ", " ERIE"], "42": ["Cretan princess of myth ", " ARIADNE"], "43": ["Passing remark? ", " YEAVOTE"], "49": ["High Court name ", " ELENA"], "51": ["Recent spirited role for Will Smith ", " GENIE"], "53": ["Fully absorbed ", " RAPT"], "54": ["Vegan's gelatin alternative ", " AGAR"], "55": ["Name related to Ivana ", " JONI"], "56": ["Fall semifinal ", " ALCS"], "57": ["''Ew-w-w!'' ", " BLEH"], "60": ["'80s First Son ", " RON"], "61": ["Zin, for instance ", " RED"]}}, "grid": [[["1", "D"], ["2", "E"], ["3", "F"], ["4", "A"], ["5", "M"], ["6", "A"], ["7", "T"], ["8", "I"], ["9", "O"], ["10", "N"], "BLACK", ["11", "P"], ["12", "S"], ["13", "S"], ["14", "T"]], [["15", "I"], ["", "N"], ["", "E"], ["", "X"], ["", "O"], ["", "R"], ["", "A"], ["", "B"], ["", "L"], ["", "E"], "BLACK", ["16", "O"], ["", "W"], ["", "I"], ["", "E"]], [["17", "S"], ["", "T"], ["", "R"], ["", "E"], ["", "A"], ["", "M"], ["", "B"], ["", "E"], ["", "D"], ["", "S"], "BLACK", ["18", "P"], ["", "A"], ["", "N"], ["", "T"]], [["19", "C"], ["", "O"], ["", "N"], "BLACK", ["20", "T"], ["", "E"], ["", "S"], ["", "T"], "BLACK", ["21", "T"], ["22", "W"], ["", "I"], ["", "N"], ["", "G"], ["", "E"]], ["BLACK", "BLACK", "BLACK", ["23", "G"], ["", "S"], ["", "N"], "BLACK", "BLACK", ["24", "P"], ["", "I"], ["", "A"], ["", "N"], ["", "O"], ["", "L"], ["", "A"]], [["25", "H"], ["26", "O"], ["27", "P"], ["", "E"], "BLACK", ["28", "I"], ["29", "S"], ["30", "L"], ["", "A"], ["", "N"], ["", "D"], "BLACK", ["31", "R"], ["", "E"], ["", "T"]], [["32", "O"], ["", "N"], ["", "A"], ["", "N"], "BLACK", ["33", "A"], ["", "T"], ["", "I"], ["", "N"], ["", "G"], ["", "E"], "BLACK", ["34", "C"], ["", "L"], ["", "E"]], [["35", "O"], ["", "E"], ["", "S"], ["", "T"], ["36", "E"], "BLACK", ["37", "A"], ["", "B"], ["", "E"], "BLACK", ["38", "R"], ["39", "E"], ["", "H"], ["", "I"], ["", "T"]], [["40", "F"], ["", "A"], ["", "T"], "BLACK", ["41", "N"], ["42", "A"], ["", "M"], ["", "E"], ["", "L"], ["43", "Y"], "BLACK", ["44", "R"], ["", "I"], ["", "F"], ["", "E"]], [["45", "P"], ["", "T"], ["", "A"], "BLACK", ["46", "O"], ["", "R"], ["", "E"], ["", "L"], ["", "S"], ["", "E"], "BLACK", ["47", "I"], ["", "D"], ["", "E"], ["", "S"]], [["48", "R"], ["", "A"], ["", "M"], ["49", "E"], ["", "K"], ["", "I"], ["", "N"], "BLACK", "BLACK", ["50", "A"], ["51", "G"], ["", "E"], "BLACK", "BLACK", "BLACK"], [["52", "I"], ["", "T"], ["", "A"], ["", "L"], ["", "I"], ["", "A"], "BLACK", ["53", "R"], ["54", "A"], ["", "V"], ["", "E"], "BLACK", ["55", "J"], ["56", "A"], ["57", "B"]], [["58", "N"], ["", "I"], ["", "K"], ["", "E"], "BLACK", ["59", "D"], ["60", "R"], ["", "A"], ["", "G"], ["", "O"], ["", "N"], ["61", "R"], ["", "O"], ["", "L"], ["", "L"]], [["62", "T"], ["", "M"], ["", "E"], ["", "N"], "BLACK", ["63", "N"], ["", "O"], ["", "P"], ["", "A"], ["", "T"], ["", "I"], ["", "E"], ["", "N"], ["", "C"], ["", "E"]], [["64", "S"], ["", "E"], ["", "R"], ["", "A"], "BLACK", ["65", "E"], ["", "N"], ["", "T"], ["", "R"], ["", "E"], ["", "E"], ["", "D"], ["", "I"], ["", "S"], ["", "H"]]]}