{"metadata": {"date": null, "rows": 15, "cols": 15}, "clues": {"across": {"1": ["Peas' natural holders ", " PODS"], "5": ["Skeptical ", " WARY"], "9": ["Team supporter ", " FAN"], "12": ["Brother of Moses ", " AARON"], "13": ["Dutch Caribbean island ", " ARUBA"], "14": ["Wedding assent ", " IDO"], "15": ["Shorthand expert, for short ", " STENO"], "16": ["Battlefield healer ", " MEDIC"], "17": ["''Ready or __, here . . . '' ", " NOT"], "18": ["Very close horse race ", " PHOTOFINISH"], "20": ["''My lips __ sealed!'' ", " ARE"], "21": ["Tablet for writing ", " PAD"], "22": ["Ceramic floor pieces ", " TILES"], "24": ["Topped, as pretzels ", " SALTED"], "28": ["''C'mon already!'' ", " LETSGO"], "31": ["Crisscross clothing pattern ", " PLAID"], "32": ["Hard-to-please actress ", " DIVA"], "33": ["Sci-fi saucers, for short ", " UFOS"], "36": ["Toward sunrise ", " EAST"], "37": ["Powder for copy machines ", " TONER"], "38": ["Puffy hairdo ", " AFRO"], "39": ["HANDLE __ CARE ", " WITH"], "40": ["Spanish cheers ", " OLES"], "41": ["Sinister smile ", " SNEER"], "42": ["Nonconformists ", " REBELS"], "44": ["Thinly scattered ", " SPARSE"], "45": ["The ones right here ", " THESE"], "47": ["Twosome ", " DUO"], "48": ["__ in ''Robert'' ", " RAS"], "49": ["Typical fairy-tale conclusion ", " HAPPYENDING"], "57": ["Numero __ (the boss) ", " UNO"], "58": ["Well-informed ", " AWARE"], "59": ["Aladdin's magical pal ", " GENIE"], "60": ["Neither's partner ", " NOR"], "61": ["Soldier's bravery ", " VALOR"], "62": ["Exclusive group ", " ELITE"], "63": ["Model airplane package ", " KIT"], "64": ["Keep one's __ on (watch) ", " EYES"], "65": ["Location ", " SITE"]}, "down": {"1": ["Hiking route ", " PATH"], "2": ["Triple-decker cookie ", " OREO"], "3": ["''__ you dare!'' ", " DONT"], "4": ["Was a busybody ", " SNOOPED"], "5": ["Small songbird ", " WREN"], "6": ["German auto ", " AUDI"], "7": ["Slugger's stats: Abbr. ", " RBIS"], "8": ["Luxurious boats ", " YACHTS"], "9": ["Negotiation ultimatum ", " FINALOFFER"], "10": ["Like very much ", " ADORE"], "11": ["Short memos ", " NOTES"], "12": ["Nile serpent ", " ASP"], "13": ["At the center of ", " AMID"], "19": ["Passing craze ", " FAD"], "23": ["Mexican lizard pet for some ", " IGUANA"], "24": ["Gush like a volcano ", " SPEW"], "25": ["Jai __ (fast-moving sport) ", " ALAI"], "26": ["Desperate strategy ", " LASTRESORT"], "27": ["Ten-percent donations ", " TITHES"], "28": ["Sentences in film scripts ", " LINES"], "29": ["Days before holidays ", " EVES"], "30": ["Driveway material ", " TAR"], "32": ["GI Joe or Barbie ", " DOLL"], "34": ["Rocks from mines ", " ORES"], "35": ["Feeling achy ", " SORE"], "37": ["Any of five on a foot ", " TOE"], "41": ["Kitchen spill absorbers ", " SPONGES"], "43": ["Mind one's manners ", " BEHAVE"], "44": ["Take to court ", " SUE"], "45": ["Place for a spare tire ", " TRUNK"], "46": ["Vietnam's capital ", " HANOI"], "47": ["Person coloring clothing ", " DYER"], "50": ["On vacation ", " AWAY"], "51": ["Not bright, as colors ", " PALE"], "52": ["Full-time athletes ", " PROS"], "53": ["Local sandwich shop ", " DELI"], "54": ["''What's __ for me?'' ", " INIT"], "55": ["Evening, on marquees ", " NITE"], "56": ["''Wow!'' ", " GEE"]}}, "grid": [["BLACK", ["1", "P"], ["2", "O"], ["3", "D"], ["4", "S"], "BLACK", "BLACK", ["5", "W"], ["6", "A"], ["7", "R"], ["8", "Y"], "BLACK", ["9", "F"], ["10", "A"], ["11", "N"]], [["12", "A"], ["", "A"], ["", "R"], ["", "O"], ["", "N"], "BLACK", ["13", "A"], ["", "R"], ["", "U"], ["", "B"], ["", "A"], "BLACK", ["14", "I"], ["", "D"], ["", "O"]], [["15", "S"], ["", "T"], ["", "E"], ["", "N"], ["", "O"], "BLACK", ["16", "M"], ["", "E"], ["", "D"], ["", "I"], ["", "C"], "BLACK", ["17", "N"], ["", "O"], ["", "T"]], [["18", "P"], ["", "H"], ["", "O"], ["", "T"], ["", "O"], ["19", "F"], ["", "I"], ["", "N"], ["", "I"], ["", "S"], ["", "H"], "BLACK", ["20", "A"], ["", "R"], ["", "E"]], ["BLACK", "BLACK", "BLACK", "BLACK", ["21", "P"], ["", "A"], ["", "D"], "BLACK", "BLACK", "BLACK", ["22", "T"], ["23", "I"], ["", "L"], ["", "E"], ["", "S"]], [["24", "S"], ["25", "A"], ["26", "L"], ["27", "T"], ["", "E"], ["", "D"], "BLACK", ["28", "L"], ["29", "E"], ["30", "T"], ["", "S"], ["", "G"], ["", "O"], "BLACK", "BLACK"], [["31", "P"], ["", "L"], ["", "A"], ["", "I"], ["", "D"], "BLACK", ["32", "D"], ["", "I"], ["", "V"], ["", "A"], "BLACK", ["33", "U"], ["", "F"], ["34", "O"], ["35", "S"]], [["36", "E"], ["", "A"], ["", "S"], ["", "T"], "BLACK", ["37", "T"], ["", "O"], ["", "N"], ["", "E"], ["", "R"], "BLACK", ["38", "A"], ["", "F"], ["", "R"], ["", "O"]], [["39", "W"], ["", "I"], ["", "T"], ["", "H"], "BLACK", ["40", "O"], ["", "L"], ["", "E"], ["", "S"], "BLACK", ["41", "S"], ["", "N"], ["", "E"], ["", "E"], ["", "R"]], ["BLACK", "BLACK", ["42", "R"], ["", "E"], ["43", "B"], ["", "E"], ["", "L"], ["", "S"], "BLACK", ["44", "S"], ["", "P"], ["", "A"], ["", "R"], ["", "S"], ["", "E"]], [["45", "T"], ["46", "H"], ["", "E"], ["", "S"], ["", "E"], "BLACK", "BLACK", "BLACK", ["47", "D"], ["", "U"], ["", "O"], "BLACK", "BLACK", "BLACK", "BLACK"], [["48", "R"], ["", "A"], ["", "S"], "BLACK", ["49", "H"], ["50", "A"], ["51", "P"], ["52", "P"], ["", "Y"], ["", "E"], ["", "N"], ["53", "D"], ["54", "I"], ["55", "N"], ["56", "G"]], [["57", "U"], ["", "N"], ["", "O"], "BLACK", ["58", "A"], ["", "W"], ["", "A"], ["", "R"], ["", "E"], "BLACK", ["59", "G"], ["", "E"], ["", "N"], ["", "I"], ["", "E"]], [["60", "N"], ["", "O"], ["", "R"], "BLACK", ["61", "V"], ["", "A"], ["", "L"], ["", "O"], ["", "R"], "BLACK", ["62", "E"], ["", "L"], ["", "I"], ["", "T"], ["", "E"]], [["63", "K"], ["", "I"], ["", "T"], "BLACK", ["64", "E"], ["", "Y"], ["", "E"], ["", "S"], "BLACK", "BLACK", ["65", "S"], ["", "I"], ["", "T"], ["", "E"], "BLACK"]]}