{"metadata": {"date": null, "rows": 15, "cols": 15}, "clues": {"across": {"1": ["Toast for tots ", " ZWIEBACK"], "9": ["Certain Summer Olympics sound ", " SPLASH"], "15": ["Anthem turning 50 next year ", " IAMWOMAN"], "16": ["Get into gear ", " CLOTHE"], "17": ["Crude path ", " PIPELINE"], "18": ["Six-time director of Bogart ", " HUSTON"], "19": ["Revered Fr. figure ", " STE"], "20": ["Hymns of gratitude ", " TEDEUMS"], "22": ["Taxpayer Advocate employer ", " IRS"], "23": ["Geometric segments ", " ARCS"], "25": ["Intrinsically, legally ", " IPSOFACTO"], "27": ["About 25% of the UN ", " ASIA"], "28": ["Once-popular organizers ", " PDAS"], "29": ["Name that means ''bear cub'' ", " ORSON"], "30": ["Related precisely ", " WELLTOLD"], "32": ["Creator of a ''Gossip Girl'' design line ", " SUI"], "33": ["Great feeling ", " ECSTASY"], "34": ["Got into in a hurry ", " THREWON"], "38": ["CNN programming note postscript ", " EST"], "39": ["Big name in brake fluid ", " PRESTONE"], "40": ["Be reminiscent (of) ", " SMACK"], "43": ["Stuffy ", " PRIM"], "44": ["Emu sextet ", " TOES"], "45": ["Speculative stock, so to speak ", " HIGHFLIER"], "47": ["Flits (about) ", " GADS"], "48": ["It's like ''-like'' ", " INE"], "49": ["Breakfast for babies ", " OATMEAL"], "51": ["UPS concerns ", " WTS"], "53": ["Become depleted ", " RUNDRY"], "55": ["''Your snow job won't work'' ", " IMNOFOOL"], "57": ["Turn down ", " REDUCE"], "58": ["Carried by galleys ", " SEABORNE"], "59": ["Impresario ", " STAGER"], "60": ["Prestigious ", " ESTEEMED"]}, "down": {"1": ["Numbers on letters ", " ZIPS"], "2": ["Request for the impatient ", " WAITASEC"], "3": ["Jeopardizes ", " IMPERILS"], "4": ["Beast that sounds like a tree ", " EWE"], "5": ["Leaves suddenly ", " BOLTS"], "6": ["Future fianc\u00e9e, maybe ", " AMIE"], "7": ["Without reservations ", " CANDIDLY"], "8": ["Roller derby accessory ", " KNEEPAD"], "9": ["Jerk ", " SCHMO"], "10": ["Retro golf pants ", " PLUSFOURS"], "11": ["Start of several New Mexico place names ", " LOS"], "12": ["Unfinished stories, often ", " ATTICS"], "13": ["Block letter ", " SHORTO"], "14": ["Name associated with Oz ", " HENSON"], "21": ["''Nautilus'' designation ", " USS"], "24": ["School boasting 18 Physics Nobelists ", " CALTECH"], "26": ["''Marriage of Figaro'' piece ", " ARIETTA"], "27": ["Electrify ", " AWE"], "28": ["Naval station ", " POST"], "31": ["Focus group ", " TASKFORCE"], "32": ["Ancestor of Abraham ", " SHEM"], "34": ["Peloponnesian War vessels ", " TRIREMES"], "35": ["Hole maker in furniture ", " WOODWORM"], "36": ["Dozen+ British pounds ", " ONESTONE"], "37": ["''Super'' console ", " NES"], "39": ["What a screenwriter starts with ", " PREMISE"], "40": ["Prepares eggs for custard ", " SHIRRS"], "41": ["''Marriage of Figaro'' piece ", " MINUET"], "42": ["Web of ulterior motives ", " AGENDA"], "43": ["Composting place ", " PIT"], "46": ["Echelon ", " LAYER"], "47": ["''Daily Planet'' logo ", " GLOBE"], "50": ["MS education major at Johns Hopkins ", " ANAT"], "52": ["Tireless runner ", " SLED"], "54": ["Was more than superficial ", " DUG"], "56": ["Hostile force ", " FOE"]}}, "grid": [[["1", "Z"], ["2", "W"], ["3", "I"], ["4", "E"], ["5", "B"], ["6", "A"], ["7", "C"], ["8", "K"], "BLACK", ["9", "S"], ["10", "P"], ["11", "L"], ["12", "A"], ["13", "S"], ["14", "H"]], [["15", "I"], ["", "A"], ["", "M"], ["", "W"], ["", "O"], ["", "M"], ["", "A"], ["", "N"], "BLACK", ["16", "C"], ["", "L"], ["", "O"], ["", "T"], ["", "H"], ["", "E"]], [["17", "P"], ["", "I"], ["", "P"], ["", "E"], ["", "L"], ["", "I"], ["", "N"], ["", "E"], "BLACK", ["18", "H"], ["", "U"], ["", "S"], ["", "T"], ["", "O"], ["", "N"]], [["19", "S"], ["", "T"], ["", "E"], "BLACK", ["20", "T"], ["", "E"], ["", "D"], ["", "E"], ["21", "U"], ["", "M"], ["", "S"], "BLACK", ["22", "I"], ["", "R"], ["", "S"]], ["BLACK", ["23", "A"], ["", "R"], ["24", "C"], ["", "S"], "BLACK", ["25", "I"], ["", "P"], ["", "S"], ["", "O"], ["", "F"], ["26", "A"], ["", "C"], ["", "T"], ["", "O"]], [["27", "A"], ["", "S"], ["", "I"], ["", "A"], "BLACK", ["28", "P"], ["", "D"], ["", "A"], ["", "S"], "BLACK", ["29", "O"], ["", "R"], ["", "S"], ["", "O"], ["", "N"]], [["30", "W"], ["", "E"], ["", "L"], ["", "L"], ["31", "T"], ["", "O"], ["", "L"], ["", "D"], "BLACK", ["32", "S"], ["", "U"], ["", "I"], "BLACK", "BLACK", "BLACK"], [["33", "E"], ["", "C"], ["", "S"], ["", "T"], ["", "A"], ["", "S"], ["", "Y"], "BLACK", ["34", "T"], ["", "H"], ["", "R"], ["", "E"], ["35", "W"], ["36", "O"], ["37", "N"]], ["BLACK", "BLACK", "BLACK", ["38", "E"], ["", "S"], ["", "T"], "BLACK", ["39", "P"], ["", "R"], ["", "E"], ["", "S"], ["", "T"], ["", "O"], ["", "N"], ["", "E"]], [["40", "S"], ["41", "M"], ["42", "A"], ["", "C"], ["", "K"], "BLACK", ["43", "P"], ["", "R"], ["", "I"], ["", "M"], "BLACK", ["44", "T"], ["", "O"], ["", "E"], ["", "S"]], [["45", "H"], ["", "I"], ["", "G"], ["", "H"], ["", "F"], ["46", "L"], ["", "I"], ["", "E"], ["", "R"], "BLACK", ["47", "G"], ["", "A"], ["", "D"], ["", "S"], "BLACK"], [["48", "I"], ["", "N"], ["", "E"], "BLACK", ["49", "O"], ["", "A"], ["", "T"], ["", "M"], ["", "E"], ["50", "A"], ["", "L"], "BLACK", ["51", "W"], ["", "T"], ["52", "S"]], [["53", "R"], ["", "U"], ["", "N"], ["54", "D"], ["", "R"], ["", "Y"], "BLACK", ["55", "I"], ["", "M"], ["", "N"], ["", "O"], ["56", "F"], ["", "O"], ["", "O"], ["", "L"]], [["57", "R"], ["", "E"], ["", "D"], ["", "U"], ["", "C"], ["", "E"], "BLACK", ["58", "S"], ["", "E"], ["", "A"], ["", "B"], ["", "O"], ["", "R"], ["", "N"], ["", "E"]], [["59", "S"], ["", "T"], ["", "A"], ["", "G"], ["", "E"], ["", "R"], "BLACK", ["60", "E"], ["", "S"], ["", "T"], ["", "E"], ["", "E"], ["", "M"], ["", "E"], ["", "D"]]]}